<?xml version="1.0" encoding="UTF-8"?>
<Supermarket id="1">
    <employees>
        <employee>
            <firstName>John</firstName>
            <lastName>Doe</lastName>
            <age>25</age>
            <contratationDate>2022-01-10</contratationDate>
        </employee>
    </employees>
    <product>
        <productName>Example Product</productName>
        <productPrice>10</productPrice>
        <productCategory>Example Category</productCategory>
        <expirationDate>2023-01-01</expirationDate>
    </product>
    <equipment>
        <equipmentName>Example Equipment</equipmentName>
        <equipmentType>Example Type</equipmentType>
    </equipment>
    <provider>
        <providerName>Example Provider</providerName>
        <providerType>Example Type</providerType>
    </provider>
    <supermarketName>Example Supermarket</supermarketName>
    <openingDate>11/11/2022</openingDate>
</Supermarket>